malhasher/CheakHash.py
malhasher/__init__.py
malhasher/sha1.py
malhasher/sha256.py
malhasher/data/MRHASHER_dataset.csv
MALHasher-1.2.dist-info/METADATA
MALHasher-1.2.dist-info/WHEEL
MALHasher-1.2.dist-info/top_level.txt
MALHasher-1.2.dist-info/RECORD
