Metadata-Version: 2.1
Name: MALHasher
Version: 1.2
Summary: A custom hash package including SHA256 and SHA1
Home-page: https://github.com/codewithjoymondal/
Author: Joy Mondal
Author-email: contact.joymondal@gmail.com
Classifier: Programming Language :: Python :: 3
Classifier: License :: OSI Approved :: MIT License
Classifier: Operating System :: OS Independent
Requires-Python: >=3.6
